{
  "07f260f4-466c-4607-9a33-f7273b24f1b4": {
    "_id": "07f260f4-466c-4607-9a33-f7273b24f1b4",
    "firstName": "Stefan",
    "lastName": "Hristov",
    "email": "test@mail.bg",
    "username": "test",
    "dateOfBirth": "03/03/1978",
    "phoneNumber": "+1 888 243346",
    "createdAt": "2023-11-01T07:22:00.358Z",
    "updatedAt": "2023-11-01T07:22:00.358Z",
    "password": "1234",
    "imageUrl": "https://img.freepik.com/free-vector/mysterious-mafia-man-smoking-cigarette_52683-34828.jpg?size=626&ext=jpg",
    "address": {
      "streetNumber": "",
      "street": "",
      "city": "Sofia",
      "country": "Bulgaria"
    },
    "friends": [],
    "notes": {
      "6f48602b-df18-4d96-bbf2-3de564d41f5e": {
        "_id": "6f48602b-df18-4d96-bbf2-3de564d41f5e",
        "position": 1,
        "title": "Title 1",
        "content": "Some random text like lorem ipsum 1",
        "isArchived": false,
        "startDate": "03/02/2021",
        "dueDate": "23/04/2025",
        "completedOn": "",
        "trackProgress": "",
        "sharedWith": [
          "5c11fd6e-649e-43d4-899e-81fc67b68aaf",
          "337cb0cd-6ecf-42d1-ba88-4133ae5c86be"
        ]
      },
      "fbae7a7c-89de-485d-9af1-f115e0ec5965": {
        "_id": "fbae7a7c-89de-485d-9af1-f115e0ec5965",
        "position": 2,
        "title": "Title 2",
        "content": "Some random text like lorem ipsum 2",
        "isArchived": true,
        "startDate": "06/11/2021",
        "dueDate": "03/05/2024",
        "completedOn": "",
        "trackProgress": "",
        "sharedWith": [
          "7b9122aa-4083-44c2-8844-245b9e5d9843",
          "37bdab71-0547-439a-9c46-3a9cb0c1441a"
        ]
      },
      "4bbcca04-7754-4f9b-a140-65e05a7d838e": {
        "_id": "4bbcca04-7754-4f9b-a140-65e05a7d838e",
        "position": 3,
        "title": "Title 3",
        "content": "Some random text like lorem ipsum 3",
        "isArchived": true,
        "startDate": "15/04/2021",
        "dueDate": "22/05/2024",
        "completedOn": "",
        "trackProgress": "",
        "sharedWith": [
          "9a03c433-42a1-4171-8085-c9146406cd54",
          "0c0f391a-f172-43ff-bfb5-38988123c8c6"
        ]
      },
      "7e9586c1-3fb3-47b3-a2d6-b044ce2ebf8a": {
        "_id": "7e9586c1-3fb3-47b3-a2d6-b044ce2ebf8a",
        "position": 4,
        "title": "Title 4",
        "content": "Some random text like lorem ipsum 4",
        "isArchived": false,
        "startDate": "07/05/2023",
        "dueDate": "11/10/2024",
        "completedOn": "",
        "trackProgress": "",
        "sharedWith": [
          "50ced80b-e6b3-48aa-9cc6-6972439d6314",
          "8bc30713-0ca0-41a1-88be-db8916935736"
        ]
      },
      "3d170bbb-93f4-4907-b085-493d36cf5a9b": {
        "_id": "3d170bbb-93f4-4907-b085-493d36cf5a9b",
        "position": 5,
        "title": "Title 5",
        "content": "Some random text like lorem ipsum 5",
        "isArchived": false,
        "startDate": "20/01/2022",
        "dueDate": "11/11/2025",
        "completedOn": "",
        "trackProgress": "",
        "sharedWith": [
          "39e16ca6-057e-435e-a8d6-1f613204459d",
          "5f02b8e3-b50a-4182-8808-9b25af57f757"
        ]
      },
      "b5dc568d-4ed2-4fd2-804b-85a168e1c51f": {
        "_id": "b5dc568d-4ed2-4fd2-804b-85a168e1c51f",
        "position": 6,
        "title": "Title 6",
        "content": "Some random text like lorem ipsum 6",
        "isArchived": false,
        "startDate": "17/07/2023",
        "dueDate": "13/04/2024",
        "completedOn": "",
        "trackProgress": "",
        "sharedWith": [
          "62137588-db15-4172-ae99-29c2d50313be",
          "9a5b2552-38bf-40ad-8b06-7fcc8c700919"
        ]
      },
      "1d21a209-7e69-412a-842d-7813bc0aad5b": {
        "_id": "1d21a209-7e69-412a-842d-7813bc0aad5b",
        "position": 7,
        "title": "Title 7",
        "content": "Some random text like lorem ipsum 7",
        "isArchived": true,
        "startDate": "22/10/2023",
        "dueDate": "28/02/2024",
        "completedOn": "",
        "trackProgress": "",
        "sharedWith": [
          "8a730a91-c2d4-4231-a8b1-4613f99ed962",
          "45cd2cbf-4bbe-4868-a580-1d1666d862fd"
        ]
      },
      "e8b258f9-ef5f-4ce4-a1dc-50876b4652d0": {
        "_id": "e8b258f9-ef5f-4ce4-a1dc-50876b4652d0",
        "position": 8,
        "title": "Title 8",
        "content": "Some random text like lorem ipsum 8",
        "isArchived": false,
        "startDate": "02/11/2023",
        "dueDate": "28/09/2024",
        "completedOn": "",
        "trackProgress": "",
        "sharedWith": [
          "c1ead179-8ddd-4cb6-9f16-86bfed210587",
          "752d08e8-b803-437f-b868-941828c39786"
        ]
      },
      "158f57bf-0159-44de-913a-ba80a9ceb832": {
        "_id": "158f57bf-0159-44de-913a-ba80a9ceb832",
        "position": 9,
        "title": "Title 9",
        "content": "Some random text like lorem ipsum 9",
        "isArchived": false,
        "startDate": "23/11/2022",
        "dueDate": "28/05/2025",
        "completedOn": "",
        "trackProgress": "",
        "sharedWith": [
          "436ac32e-ee1a-4d14-bb86-401b44a7ead1",
          "b2596b92-11d8-4b22-8cc2-99f5d97ff680"
        ]
      },
      "2a3c13d8-c9e1-4069-a8e7-ad364e6bfac1": {
        "_id": "2a3c13d8-c9e1-4069-a8e7-ad364e6bfac1",
        "position": 10,
        "title": "Title 10",
        "content": "Some random text like lorem ipsum 10",
        "isArchived": false,
        "startDate": "23/12/2020",
        "dueDate": "16/01/2024",
        "completedOn": "",
        "trackProgress": "",
        "sharedWith": [
          "0e9eeaa1-9f90-4f7b-879a-2bae081d4dd6",
          "362977a4-4bb2-4514-967a-71ce4c7c34d5"
        ]
      },
      "4f8bb6a7-f40a-4f0c-b41a-eb9cd9533afe": {
        "_id": "4f8bb6a7-f40a-4f0c-b41a-eb9cd9533afe",
        "position": 11,
        "title": "Title 11",
        "content": "Some random text like lorem ipsum 11",
        "isArchived": true,
        "startDate": "12/05/2022",
        "dueDate": "12/10/2025",
        "completedOn": "",
        "trackProgress": "",
        "sharedWith": [
          "b1eadffc-a152-42d9-992c-e408dc241b9c",
          "475118bb-4f7a-4e8a-9c13-058b56cb920f"
        ]
      },
      "2cd86a63-8cfe-4666-9d47-02066d0a420e": {
        "_id": "2cd86a63-8cfe-4666-9d47-02066d0a420e",
        "position": 12,
        "title": "Title 12",
        "content": "Some random text like lorem ipsum 12",
        "isArchived": true,
        "startDate": "11/08/2021",
        "dueDate": "24/05/2024",
        "completedOn": "",
        "trackProgress": "",
        "sharedWith": [
          "d3ebbe1b-4bfd-4733-a491-aad0f84f0f15",
          "fde7000e-aceb-44ab-8494-8ad0d7178a73"
        ]
      },
      "a540c303-1bd3-474b-aabe-e5df64a173c9": {
        "_id": "a540c303-1bd3-474b-aabe-e5df64a173c9",
        "position": 13,
        "title": "Title 13",
        "content": "Some random text like lorem ipsum 13",
        "isArchived": false,
        "startDate": "14/01/2023",
        "dueDate": "10/02/2025",
        "completedOn": "",
        "trackProgress": "",
        "sharedWith": [
          "c6e52164-6038-4066-962d-9bd1e63769af",
          "2014fc75-9f3f-4bef-b187-ffd1d0ab76b4"
        ]
      },
      "7cfad1dd-2827-4406-a585-608d52b08221": {
        "_id": "7cfad1dd-2827-4406-a585-608d52b08221",
        "position": 14,
        "title": "Title 14",
        "content": "Some random text like lorem ipsum 14",
        "isArchived": true,
        "startDate": "22/01/2023",
        "dueDate": "06/06/2025",
        "completedOn": "",
        "trackProgress": "",
        "sharedWith": [
          "618bafb9-34ef-4209-8c8d-234e75021e11",
          "677d36cb-b449-4430-8783-179bc64d6944"
        ]
      },
      "9caed434-d545-45c3-a61d-a1d0844bc30c": {
        "_id": "9caed434-d545-45c3-a61d-a1d0844bc30c",
        "position": 15,
        "title": "Title 15",
        "content": "Some random text like lorem ipsum 15",
        "isArchived": false,
        "startDate": "03/02/2020",
        "dueDate": "13/03/2024",
        "completedOn": "",
        "trackProgress": "",
        "sharedWith": [
          "41183802-d7ba-4c6c-ba52-6faa9f206674",
          "694f980a-0659-4a18-a7e3-b6634952a930"
        ]
      },
      "66ba6712-24c4-47c0-93f2-2fe8e65d54aa": {
        "_id": "66ba6712-24c4-47c0-93f2-2fe8e65d54aa",
        "position": 16,
        "title": "Title 16",
        "content": "Some random text like lorem ipsum 16",
        "isArchived": false,
        "startDate": "11/04/2022",
        "dueDate": "03/09/2024",
        "completedOn": "",
        "trackProgress": "",
        "sharedWith": [
          "13d1376f-7364-471f-b4e8-f1bc7300cd55",
          "67690107-3177-450a-852f-be08c58ce3e9"
        ]
      },
      "395e7abb-da17-47d4-a6e8-9b62eb8287fa": {
        "_id": "395e7abb-da17-47d4-a6e8-9b62eb8287fa",
        "position": 17,
        "title": "Title 17",
        "content": "Some random text like lorem ipsum 17",
        "isArchived": false,
        "startDate": "06/05/2021",
        "dueDate": "18/06/2024",
        "completedOn": "",
        "trackProgress": "",
        "sharedWith": [
          "72de2baf-8947-4173-bcc6-f05fbbdee3a4",
          "8235f597-721a-4d50-908e-f0c4df1ae3f9"
        ]
      },
      "29f2832b-c46d-4452-9b4e-6c2c5277dd79": {
        "_id": "29f2832b-c46d-4452-9b4e-6c2c5277dd79",
        "position": 18,
        "title": "Title 18",
        "content": "Some random text like lorem ipsum 18",
        "isArchived": false,
        "startDate": "23/05/2022",
        "dueDate": "18/09/2025",
        "completedOn": "",
        "trackProgress": "",
        "sharedWith": [
          "5206945c-e8bd-45d9-95c8-885fcbb0842f",
          "c3c51606-0d3a-4a5f-b463-be29046e4d8d"
        ]
      },
      "95078783-e25f-43e8-8edc-a12bd04459f4": {
        "_id": "95078783-e25f-43e8-8edc-a12bd04459f4",
        "position": 19,
        "title": "Title 19",
        "content": "Some random text like lorem ipsum 19",
        "isArchived": true,
        "startDate": "03/11/2022",
        "dueDate": "13/08/2025",
        "completedOn": "",
        "trackProgress": "",
        "sharedWith": [
          "b0436fe3-0c36-4594-8f30-9b1422d3270a",
          "ab7ab705-03df-4df4-b6af-179aaa726a6e"
        ]
      },
      "a6a96641-a6b2-49d6-aca3-30a5ef2c0f11": {
        "_id": "a6a96641-a6b2-49d6-aca3-30a5ef2c0f11",
        "position": 20,
        "title": "Title 20",
        "content": "Some random text like lorem ipsum 20",
        "isArchived": true,
        "startDate": "22/09/2022",
        "dueDate": "18/08/2025",
        "completedOn": "",
        "trackProgress": "",
        "sharedWith": [
          "3200ea79-979a-477d-93c8-bb2dc8c26db5",
          "8186cbfa-fff3-4af9-a685-85c3b07c3298"
        ]
      }
    },
    "checklists": {
      "c4864ad0-6ebd-445e-ae46-22af623ba76d": {
        "_id": "c4864ad0-6ebd-445e-ae46-22af623ba76d",
        "type": "General to-do/Shopping list",
        "title": "Title 1",
        "elements": {
          "c3865ad0-6cbd-445e-ae46-22ag624ba74d": {
            "_id": "c3865ad0-6cbd-445e-ae46-22ag624ba74d",
            "position": 1,
            "content": "element 1 of checklist 1",
            "dueDate": "22/05/2025",
            "status": "Not started/Pending",
            "note": "additional info"
          },
          "c3664bd0-6cbd-445e-ac46-22bg624ba74c": {
            "_id": "c3664bd0-6cbd-445e-ac46-22bg624ba74c",
            "position": 2,
            "content": "element 2 of checklist 1",
            "dueDate": "14/10/2024",
            "status": "In progress/NA",
            "note": ""
          },
          "c3864ad0-6cbd-445e-ae46-22ah624ba74a": {
            "_id": "c3864ad0-6cbd-445e-ae46-22ah624ba74a",
            "position": 3,
            "content": "element 3 of checklist 1",
            "dueDate": "27/08/2025",
            "status": "Done",
            "note": ""
          }
        },
        "sharedWith": [
          "fb3277e2-979b-4587-b9c1-da0ffbd0c9fa",
          "5f126aa9-aa43-4e6c-9b04-c85776ff3b83"
        ],
        "isArchived": true,
        "dueDate": "21/02/2024"
      },
      "d1afcfe3-3c5e-4085-a923-1ad46499e36e": {
        "_id": "d1afcfe3-3c5e-4085-a923-1ad46499e36e",
        "type": "General to-do/Shopping list",
        "title": "Title 2",
        "elements": {
          "c3865ad0-6cbd-445e-ae46-22ag624ba74d": {
            "_id": "c3865ad0-6cbd-445e-ae46-22ag624ba74d",
            "position": 1,
            "content": "element 1 of checklist 1",
            "dueDate": "22/05/2025",
            "status": "Not started/Pending",
            "note": "additional info"
          },
          "c3664bd0-6cbd-445e-ac46-22bg624ba74c": {
            "_id": "c3664bd0-6cbd-445e-ac46-22bg624ba74c",
            "position": 2,
            "content": "element 2 of checklist 1",
            "dueDate": "14/10/2024",
            "status": "In progress/NA",
            "note": ""
          },
          "c3864ad0-6cbd-445e-ae46-22ah624ba74a": {
            "_id": "c3864ad0-6cbd-445e-ae46-22ah624ba74a",
            "position": 3,
            "content": "element 3 of checklist 1",
            "dueDate": "27/08/2025",
            "status": "Done",
            "note": ""
          }
        },
        "sharedWith": [
          "8b877604-22f3-4926-8a8e-718ed434d929",
          "18a74e46-bf1d-4304-b4b4-30ab9f85be9f"
        ],
        "isArchived": true,
        "dueDate": "27/04/2025"
      },
      "f15f8cb3-4f48-4896-b1c4-040b4ddd8cb4": {
        "_id": "f15f8cb3-4f48-4896-b1c4-040b4ddd8cb4",
        "type": "General to-do/Shopping list",
        "title": "Title 3",
        "elements": {
          "c3864ad0-6cbd-445e-ae46-22ag624ba74d": {
            "_id": "c3864ad0-6cbd-445e-ae46-22ag624ba74d",
            "position": 1,
            "content": "element 1 of checklist 3",
            "dueDate": "16/04/2024",
            "status": "Not started/Pending",
            "note": "additional info"
          },
          "c3664ad0-6cbd-445e-ae46-22bg624ba74c": {
            "_id": "c3664ad0-6cbd-445e-ae46-22bg624ba74c",
            "position": 2,
            "content": "element 2 of checklist 3",
            "dueDate": "16/04/2024",
            "status": "In progress/NA",
            "note": ""
          },
          "c3864ad0-6cbd-445e-ae46-22ah624ba74a": {
            "_id": "c3864ad0-6cbd-445e-ae46-22ah624ba74a",
            "position": 3,
            "content": "element 3 of checklist 3",
            "dueDate": "27/03/2024",
            "status": "Done",
            "note": ""
          }
        },
        "sharedWith": [
          "2e9f8cb7-139c-4798-bb05-b307ccb1999c",
          "50466695-cefd-4f66-80bf-b5d01d3a0f61"
        ],
        "isArchived": true,
        "dueDate": "22/01/2024"
      },
      "c4864bd0-6ebd-442e-ae46-28af623ba74d": {
        "_id": "c4864bd0-6ebd-442e-ae46-28af623ba74d",
        "type": "General to-do/Shopping list",
        "title": "Title 1",
        "elements": {
          "c3862ad0-6cbd-445e-ae46-22ag624ba74d": {
            "_id": "c3862ad0-6cbd-445e-ae46-22ag624ba74d",
            "position": 1,
            "content": "element 1 of checklist 1",
            "dueDate": "22/05/2025",
            "status": "Not started/Pending",
            "note": "additional info"
          },
          "c3664ad0-6ccd-445e-ae46-22bg624ba74c": {
            "_id": "c3664ad0-6ccd-445e-ae46-22bg624ba74c",
            "position": 2,
            "content": "element 2 of checklist 1",
            "dueDate": "14/10/2024",
            "status": "In progress/NA",
            "note": ""
          },
          "c3864ad0-6cad-445e-ae46-22ah624ba74a": {
            "_id": "c3864ad0-6cad-445e-ae46-22ah624ba74a",
            "position": 3,
            "content": "element 3 of checklist 1",
            "dueDate": "27/08/2025",
            "status": "Done",
            "note": ""
          }
        },
        "sharedWith": [
          "fb3277e2-979b-4587-b9c1-da0ffbd0c9fa",
          "5f126aa9-aa43-4e6c-9b04-c85776ff3b83"
        ],
        "isArchived": true,
        "dueDate": "21/02/2024"
      },
      "d1afafe3-3c5e-4065-a923-1ad42499e36e": {
        "_id": "d1afafe3-3c5e-4065-a923-1ad42499e36e",
        "type": "General to-do/Shopping list",
        "title": "Title 2",
        "elements": {
          "c3861ad0-6cbd-445e-ae46-22ah624ba74a": {
            "_id": "c3861ad0-6cbd-445e-ae46-22ah624ba74a",
            "position": 1,
            "content": "element 1 of checklist 2",
            "dueDate": "31/08/2024",
            "status": "Not started/Pending",
            "note": "additional info"
          },
          "c3664ad0-6cbd-441e-ae46-22bg624ba74c": {
            "_id": "c3664ad0-6cbd-441e-ae46-22bg624ba74c",
            "position": 2,
            "content": "element 2 of checklist 2",
            "dueDate": "11/10/2024",
            "status": "In progress/NA",
            "note": ""
          },
          "c3824ad0-6cbd-445e-ae46-22ag624ba74d": {
            "_id": "c3824ad0-6cbd-445e-ae46-22ag624ba74d",
            "position": 3,
            "content": "element 3 of checklist 2",
            "dueDate": "17/08/2024",
            "status": "Done",
            "note": ""
          }
        },
        "sharedWith": [
          "8b877604-22f3-4926-8a8e-718ed434d929",
          "18a74e46-bf1d-4304-b4b4-30ab9f85be9f"
        ],
        "isArchived": true,
        "dueDate": "27/04/2025"
      }
    },
    "events": {}
  }
}